LICENSE
MANIFEST.in
README.md
setup.cfg
setup.py
streamlit_container_width/__init__.py
streamlit_container_width.egg-info/PKG-INFO
streamlit_container_width.egg-info/SOURCES.txt
streamlit_container_width.egg-info/dependency_links.txt
streamlit_container_width.egg-info/requires.txt
streamlit_container_width.egg-info/top_level.txt
streamlit_container_width/frontend/build/asset-manifest.json
streamlit_container_width/frontend/build/bootstrap.min.css
streamlit_container_width/frontend/build/index.html
streamlit_container_width/frontend/build/precache-manifest.0844cea1110debaae62d45324ed94930.js
streamlit_container_width/frontend/build/service-worker.js
streamlit_container_width/frontend/build/static/js/2.455ad4fd.chunk.js
streamlit_container_width/frontend/build/static/js/2.455ad4fd.chunk.js.LICENSE.txt
streamlit_container_width/frontend/build/static/js/2.455ad4fd.chunk.js.map
streamlit_container_width/frontend/build/static/js/main.da71244e.chunk.js
streamlit_container_width/frontend/build/static/js/main.da71244e.chunk.js.map
streamlit_container_width/frontend/build/static/js/runtime-main.42580a3e.js
streamlit_container_width/frontend/build/static/js/runtime-main.42580a3e.js.map