Metadata-Version: 2.2
Name: streamlit-container-width
Version: 1.0.3
Summary: A simple component that returns the dimensions of the container where it is rendered.
Home-page: https://github.com/edball10/streamlit-container-width
Download-URL: https://github.com/edball10/streamlit-container-width/archive/refs/tags/v1.0.3.tar.gz
Author: Edward Ball
Author-email: edward.ball@hotmail.co.uk
Requires-Python: >=3.6
License-File: LICENSE
Requires-Dist: streamlit>=0.63
Dynamic: author
Dynamic: author-email
Dynamic: description
Dynamic: description-content-type
Dynamic: download-url
Dynamic: home-page
Dynamic: requires-dist
Dynamic: requires-python
Dynamic: summary
